odoo/addons/purchase_isolated_rfq/README.rst
odoo/addons/purchase_isolated_rfq/__init__.py
odoo/addons/purchase_isolated_rfq/__manifest__.py
odoo/addons/purchase_isolated_rfq/hooks.py
odoo/addons/purchase_isolated_rfq/data/ir_sequence_data.xml
odoo/addons/purchase_isolated_rfq/i18n/purchase_isolated_rfq.pot
odoo/addons/purchase_isolated_rfq/models/__init__.py
odoo/addons/purchase_isolated_rfq/models/purchase_order.py
odoo/addons/purchase_isolated_rfq/readme/CONTRIBUTORS.rst
odoo/addons/purchase_isolated_rfq/readme/DESCRIPTION.rst
odoo/addons/purchase_isolated_rfq/readme/USAGE.rst
odoo/addons/purchase_isolated_rfq/static/description/icon.png
odoo/addons/purchase_isolated_rfq/static/description/index.html
odoo/addons/purchase_isolated_rfq/tests/__init__.py
odoo/addons/purchase_isolated_rfq/tests/test_purchase_isolated_rfq.py
odoo/addons/purchase_isolated_rfq/views/purchase_views.xml
odoo13_addon_purchase_isolated_rfq-13.0.1.1.1.dist-info/METADATA
odoo13_addon_purchase_isolated_rfq-13.0.1.1.1.dist-info/WHEEL
odoo13_addon_purchase_isolated_rfq-13.0.1.1.1.dist-info/top_level.txt
odoo13_addon_purchase_isolated_rfq-13.0.1.1.1.dist-info/RECORD
